numberdata/__init__.py
numberdata/calculate.py
numberdata-1.0.1.dist-info/LICENSE
numberdata-1.0.1.dist-info/METADATA
numberdata-1.0.1.dist-info/WHEEL
numberdata-1.0.1.dist-info/top_level.txt
numberdata-1.0.1.dist-info/RECORD
