Metadata-Version: 2.1
Name: numberdata
Version: 1.0.1
Summary: A simple package calculating values for a single number
Home-page: UNKNOWN
Author: Anuj Mokashi
Author-email: xyz@abc.com
License: UNKNOWN
Keywords: package numbers calculations
Platform: UNKNOWN
Classifier: Programming Language :: Python :: 2
Classifier: Operating System :: OS Independent
